upwork/__init__.py
upwork/scraper.py
upwork-1.0.21.dist-info/METADATA
upwork-1.0.21.dist-info/WHEEL
upwork-1.0.21.dist-info/license.txt
upwork-1.0.21.dist-info/top_level.txt
upwork-1.0.21.dist-info/RECORD
