Metadata-Version: 2.1
Name: upwork
Version: 1.0.21
Summary: Upwork talent scraper
Home-page: https://github.com/devEyosiyas/upwork_lib
Author: Eyosiyas Bereketab
Author-email: contact@deveyosiyas.com
Classifier: Programming Language :: Python :: 3
Classifier: License :: OSI Approved :: MIT License
Classifier: Operating System :: OS Independent
Requires-Python: >=3.6
License-File: license.txt
